pyfol
