Metadata-Version: 2.1
Name: PyFOL
Version: 1.1.7.4
Summary: A library that optimizes Python functions
Home-page: https://pypi.python.org/pypi/PyFOL
Author: AndyPomeloMars
Author-email: andypomelomars@163.com
License: GPL
Keywords: PyFOL python3 python py FOL
Classifier: License :: OSI Approved :: MIT License
Classifier: Programming Language :: Python
Classifier: Intended Audience :: Developers
Classifier: Operating System :: OS Independent
Requires-Python: >=3.7
